st_txt_copybutton/__init__.py
st_txt_copybutton/frontend/build/asset-manifest.json
st_txt_copybutton/frontend/build/bootstrap.min.css
st_txt_copybutton/frontend/build/index.html
st_txt_copybutton/frontend/build/static/js/main.3819276e.js
st_txt_copybutton/frontend/build/static/js/main.3819276e.js.LICENSE.txt
st_txt_copybutton/frontend/build/static/js/main.3819276e.js.map
st_txt_copybutton/frontend/build/static/js/main.3c2a97bc.js
st_txt_copybutton/frontend/build/static/js/main.3c2a97bc.js.LICENSE.txt
st_txt_copybutton/frontend/build/static/js/main.3c2a97bc.js.map
st_txt_copybutton-0.0.3.dist-info/LICENSE
st_txt_copybutton-0.0.3.dist-info/METADATA
st_txt_copybutton-0.0.3.dist-info/WHEEL
st_txt_copybutton-0.0.3.dist-info/top_level.txt
st_txt_copybutton-0.0.3.dist-info/RECORD
